{
  "recentFiles": [
    {
      "basename": "赤字空间",
      "path": "01 概念学习/经济学/赤字空间.md"
    },
    {
      "basename": "梯度",
      "path": "01 概念学习/计算机课科学/梯度.md"
    },
    {
      "basename": "傻小子和疯女人",
      "path": "09 文学批评和电影批评/傻小子和疯女人.md"
    },
    {
      "basename": "PDF Marker",
      "path": "11 Projects/02 学术论文PDF翻译润色总结发公众号/PDF Marker.md"
    },
    {
      "basename": "美国",
      "path": "00 Summary/通用知识/过去和现在的世界/世界史/美国.md"
    },
    {
      "basename": "欧洲",
      "path": "00 Summary/通用知识/过去和现在的世界/世界史/欧洲.md"
    },
    {
      "basename": "朝鲜韩国",
      "path": "00 Summary/通用知识/过去和现在的世界/世界史/朝鲜韩国.md"
    },
    {
      "basename": "古埃及",
      "path": "00 Summary/通用知识/过去和现在的世界/世界史/古埃及.md"
    },
    {
      "basename": "法国",
      "path": "00 Summary/通用知识/过去和现在的世界/世界史/法国.md"
    },
    {
      "basename": "俄罗斯",
      "path": "00 Summary/通用知识/过去和现在的世界/世界史/俄罗斯.md"
    },
    {
      "basename": "“同人”是什么，而如何发展",
      "path": "00 Summary/通用知识/传媒与传播/“同人”是什么，而如何发展.md"
    },
    {
      "basename": "《天朝的崩溃：鸦片战争再研究》",
      "path": "04 Note/非虚构/政治军事/《天朝的崩溃：鸦片战争再研究》.md"
    },
    {
      "basename": "02 商",
      "path": "00 Summary/通用知识/过去和现在的世界/中国历史/断代史/02 商.md"
    },
    {
      "basename": "03 周",
      "path": "00 Summary/通用知识/过去和现在的世界/中国历史/断代史/03 周.md"
    },
    {
      "basename": "00 Obisidian常用快捷键",
      "path": "03 Skills/产品使用/00 Obisidian常用快捷键.md"
    },
    {
      "basename": "《汴京之围：北宋末年的外交、战争和人》",
      "path": "04 Note/非虚构/政治军事/《汴京之围：北宋末年的外交、战争和人》.md"
    },
    {
      "basename": "变文",
      "path": "04 Note/通识/变文.md"
    },
    {
      "basename": "阿里云转写服务调用",
      "path": "11 Projects/01 实时语音转写/阿里云转写服务调用.md"
    },
    {
      "basename": "index",
      "path": "index.md"
    },
    {
      "basename": "第九届网络社会年会-廖雪婷：数字行动主义与男性权益运动的民粹主义浪潮",
      "path": "06  论文阅读/第九届网络社会年会-廖雪婷：数字行动主义与男性权益运动的民粹主义浪潮.md"
    },
    {
      "basename": "神奇动物在那里",
      "path": "04 Note/自然界/神奇动物在那里.md"
    },
    {
      "basename": "00 远古（夏以前）",
      "path": "00 Summary/通用知识/过去和现在的世界/中国历史/断代史/00 远古（夏以前）.md"
    },
    {
      "basename": "中国古代诗歌",
      "path": "00 Summary/通用知识/过去和现在的世界/文学/中国古代诗歌.md"
    },
    {
      "basename": "意大利",
      "path": "00 Summary/通用知识/过去和现在的世界/世界史/意大利.md"
    },
    {
      "basename": "日本",
      "path": "00 Summary/通用知识/过去和现在的世界/世界史/日本.md"
    },
    {
      "basename": "英国",
      "path": "00 Summary/通用知识/过去和现在的世界/世界史/英国.md"
    },
    {
      "basename": "鸦片战争之三大恨讨清檄文",
      "path": "04 Note/摘录/鸦片战争之三大恨讨清檄文.md"
    },
    {
      "basename": "荷兰",
      "path": "00 Summary/通用知识/过去和现在的世界/世界史/荷兰.md"
    },
    {
      "basename": "《西方思想史十二讲》",
      "path": "04 Note/非虚构/思想哲学/《西方思想史十二讲》.md"
    },
    {
      "basename": "奥地利",
      "path": "00 Summary/通用知识/过去和现在的世界/世界史/奥地利.md"
    },
    {
      "basename": "近现代的世界（1965——）",
      "path": "00 Summary/通用知识/过去和现在的世界/世界史/近现代的世界（1965——）.md"
    },
    {
      "basename": "前苏联",
      "path": "00 Summary/通用知识/过去和现在的世界/世界史/前苏联.md"
    },
    {
      "basename": "《黑箱日记》",
      "path": "04 Note/非虚构/纪录片/《黑箱日记》.md"
    },
    {
      "basename": "《黑箱：日本之耻》",
      "path": "04 Note/非虚构/纪实文学/《黑箱：日本之耻》.md"
    },
    {
      "basename": "尼采-莎乐美-里尔克",
      "path": "10 名人八卦/尼采-莎乐美-里尔克.md"
    },
    {
      "basename": "短视频如何起号",
      "path": "03 Skills/短视频/短视频如何起号.md"
    },
    {
      "basename": "Automa详解：浏览器行为自动化和我的使用",
      "path": "03 Skills/产品使用/Automa详解：浏览器行为自动化和我的使用.md"
    },
    {
      "basename": "09 舌尖上的宋韵：《山家清供》中的饮食美学",
      "path": "08 规划与执行/公众号写作存档/09 舌尖上的宋韵：《山家清供》中的饮食美学.md"
    },
    {
      "basename": "Copilot：一个插件自建知识库",
      "path": "03 Skills/工具使用/Obisidian插件/Copilot：一个插件自建知识库.md"
    },
    {
      "basename": "未命名",
      "path": "08 规划与执行/公众号写作存档/未命名.md"
    },
    {
      "basename": "08 急！恩师和我老丈人干起来了，我该怎么办？从晚唐大诗人李商隐的人生遭际看牛李党争",
      "path": "08 规划与执行/公众号写作存档/08 急！恩师和我老丈人干起来了，我该怎么办？从晚唐大诗人李商隐的人生遭际看牛李党争.md"
    },
    {
      "basename": "信息流是如何塑造我",
      "path": "08 规划与执行/信息流是如何塑造我.md"
    },
    {
      "basename": "技术演进",
      "path": "08 规划与执行/技术演进.md"
    },
    {
      "basename": "SOP不是越细越好，而是要直接给出核心效率指导",
      "path": "07 思考录/管理/SOP不是越细越好，而是要直接给出核心效率指导.md"
    },
    {
      "basename": "01 《被侮辱与被损害的人》：穷人是这么相爱，而又不得相爱；暮年是这么孤寂，而又不安于孤寂",
      "path": "08 规划与执行/公众号写作存档/01 《被侮辱与被损害的人》：穷人是这么相爱，而又不得相爱；暮年是这么孤寂，而又不安于孤寂.md"
    },
    {
      "basename": "产品灵感",
      "path": "03 Skills/产品灵感.md"
    },
    {
      "basename": "技术目录",
      "path": "03 Skills/技术目录.md"
    },
    {
      "basename": "Prompt  - 如何写提示词",
      "path": "03 Skills/AI/Prompt  - 如何写提示词.md"
    },
    {
      "basename": "高级感平面版式设计作品",
      "path": "03 Skills/设计/高级感平面版式设计作品.md"
    },
    {
      "basename": "Mermaid绘图",
      "path": "03 Skills/技术课程或书籍/绘图/Mermaid绘图.md"
    }
  ],
  "omittedPaths": [],
  "omittedTags": [],
  "updateOn": "file-open",
  "omitBookmarks": false
}